betterargs/__init__.py
betterargs/__main__.py
betterargs-0.0.3.dist-info/METADATA
betterargs-0.0.3.dist-info/WHEEL
betterargs-0.0.3.dist-info/top_level.txt
betterargs-0.0.3.dist-info/RECORD
