Metadata-Version: 2.1
Name: betterargs
Version: 0.0.3
Summary: A tool to create a command-line interface for your app using python
Home-page: UNKNOWN
Author: DanielMuringe
Author-email: <danielmuringe@gmail.com>
License: MIT
Project-URL: Source, https://www.github.com/danielmuringe/betterargs
Project-URL: Tracker, https://www.github.com/danielmuringe/betterargs/issues
Keywords: argument parser,boilerplate,yaml,command-line,command-line-tool,argparse,build tools,args
Platform: UNKNOWN
Classifier: Development Status :: 1 - Planning
Classifier: Environment :: Console
Classifier: Intended Audience :: Developers
Classifier: Intended Audience :: Science/Research
Classifier: Programming Language :: Python
Classifier: Programming Language :: Python :: 3
Classifier: Operating System :: POSIX :: Linux
Classifier: Topic :: Utilities
Classifier: Topic :: Software Development :: Build Tools
Classifier: Topic :: Software Development :: User Interfaces
Classifier: License :: OSI Approved :: MIT License
Classifier: Natural Language :: English
Requires: pyyaml
Requires-Python: >=3.10
Requires-Dist: pyyaml
